entrns/__init__.py
entrns-0.1.0.dist-info/METADATA
entrns-0.1.0.dist-info/WHEEL
entrns-0.1.0.dist-info/top_level.txt
entrns-0.1.0.dist-info/RECORD
