Metadata-Version: 2.4
Name: entrns
Version: 0.1.0
Summary: Biblioteca para crear bots simples y entrenarlos
Author-email: TuNombre <tunombre@example.com>
License: MIT
Classifier: Programming Language :: Python :: 3
Classifier: License :: OSI Approved :: MIT License
Classifier: Operating System :: OS Independent
Requires-Python: >=3.6
